dt_utils/__init__.py
dt_utils/common.py
dt_utils/format.py
dt_utils/neat.py
dt_utils/parsers.py
dt_utils/period.py
dt_utils/timers.py
dt_utils-0.0.13.dist-info/licenses/LICENSE
tests/__init__.py
tests/test_format.py
tests/test_neat.py
tests/test_parse_datetime.py
tests/test_parse_tdelta.py
dt_utils-0.0.13.dist-info/METADATA
dt_utils-0.0.13.dist-info/WHEEL
dt_utils-0.0.13.dist-info/top_level.txt
dt_utils-0.0.13.dist-info/RECORD
