Metadata-Version: 2.4
Name: dt_utils
Version: 0.0.13
Summary: Datetime utils
Home-page: https://github.com/claydodo/dt_utils
Author: claydodo and his little friends (xiao huo ban)
Author-email: claydodo@foxmail.com
Classifier: Operating System :: OS Independent
License-File: LICENSE
Requires-Dist: six
Requires-Dist: python-dateutil
Dynamic: author
Dynamic: author-email
Dynamic: classifier
Dynamic: home-page
Dynamic: license-file
Dynamic: requires-dist
Dynamic: summary
